gnip/__init__.py
gnip/gnip.py
gnip/helpers.py
python_gnip-0.0.2.dist-info/DESCRIPTION.rst
python_gnip-0.0.2.dist-info/METADATA
python_gnip-0.0.2.dist-info/RECORD
python_gnip-0.0.2.dist-info/WHEEL
python_gnip-0.0.2.dist-info/metadata.json
python_gnip-0.0.2.dist-info/top_level.txt
