Metadata-Version: 2.0
Name: python-gnip
Version: 0.0.2
Summary: Gnip Powertrack Wrapper
Home-page: https://github.com/mekza/python-bright/
Author: Martin-Zack Mekkaoui
Author-email: martin@mekkaoui.fr
License: MIT License
Keywords: gnip data twitter
Platform: UNKNOWN
Requires-Dist: requests (>=2.10.0)
